Anvil_Test-0.0.2.dist-info/DESCRIPTION.rst
Anvil_Test-0.0.2.dist-info/METADATA
Anvil_Test-0.0.2.dist-info/RECORD
Anvil_Test-0.0.2.dist-info/WHEEL
Anvil_Test-0.0.2.dist-info/metadata.json
Anvil_Test-0.0.2.dist-info/top_level.txt
anvil_test/__init__.py
anvil_test/session.py
