Metadata-Version: 2.0
Name: Anvil-Test
Version: 0.0.2
Summary: UNKNOWN
Home-page: UNKNOWN
Author: Owen Campbell
Author-email: UNKNOWN
License: The MIT License (MIT)
Platform: UNKNOWN
Classifier: License :: OSI Approved :: MIT License
Classifier: Natural Language :: English
Requires-Python: >=3.6
Requires-Dist: selenium
